adnancode/__init__.py
adnancode/vector.py
Simple_Vector_operations-1.0.dist-info/LICENSE
Simple_Vector_operations-1.0.dist-info/METADATA
Simple_Vector_operations-1.0.dist-info/WHEEL
Simple_Vector_operations-1.0.dist-info/top_level.txt
Simple_Vector_operations-1.0.dist-info/RECORD
